{
 "case_id": "sweep.uxlab",
 "db_delta": {},
 "harness_version": 1,
 "notes": "mechanical breadth sweep (admin persona)",
 "seed": 42,
 "steps": [
  {
   "calls": [
    {
     "args": {
      "channel_id": "<#general>"
     },
     "method": "send_message",
     "payload": {
      "components": [],
      "content": "❌ Command not found. Use `!help` for available commands.",
      "tts": false
     }
    },
    {
     "args": {
      "channel_id": "<#general>",
      "message_id": "<msg:1>",
      "reason": null
     },
     "method": "delete_message"
    },
    {
     "args": {
      "channel_id": "<#general>",
      "message_id": "<msg:2>"
     },
     "method": "edit_message",
     "payload": {
      "components": [
       {
        "components": [
         {
          "custom_id": "<cid:1>",
          "disabled": true,
          "emoji": {
           "id": null,
           "name": "🌑"
          },
          "label": "Overview",
          "style": 1,
          "type": 2
         },
         {
          "custom_id": "<cid:2>",
          "disabled": true,
          "label": "Sinners",
          "style": 2,
          "type": 2
         },
         {
          "custom_id": "<cid:3>",
          "disabled": true,
          "label": "Sins",
          "style": 2,
          "type": 2
         },
         {
          "custom_id": "<cid:4>",
          "disabled": true,
          "label": "Damage types",
          "style": 2,
          "type": 2
         },
         {
          "custom_id": "<cid:5>",
          "disabled": true,
          "label": "Mechanics",
          "style": 2,
          "type": 2
         }
        ],
        "type": 1
       },
       {
        "components": [
         {
          "custom_id": "<cid:6>",
          "disabled": true,
          "label": "E.G.O grades",
          "style": 2,
          "type": 2
         },
         {
          "custom_id": "<cid:7>",
          "disabled": true,
          "label": "Statuses",
          "style": 2,
          "type": 2
         },
         {
          "custom_id": "<cid:8>",
          "disabled": true,
          "emoji": {
           "id": null,
           "name": "📖"
          },
          "label": "Origins",
          "style": 2,
          "type": 2
         }
        ],
        "type": 1
       }
      ],
      "flags": 0,
      "tts": false
     }
    }
   ],
   "input": {
    "content": "!uxlab",
    "kind": "command",
    "persona": "admin"
   }
  }
 ],
 "subsystem": "ux_lab"
}
